_cntk_py.cpython-36m-x86_64-linux-gnu.so
cntk/VERSION
cntk/__init__.py
cntk/axis.py
cntk/cntk_py.py
cntk/cntk_py_init.py
cntk/conftest.py
cntk/core.py
cntk/default_options.py
cntk/device.py
cntk/initializer.py
cntk/pytest.ini
cntk/sample_installer.py
cntk/tensor.py
cntk/variables.py
cntk/contrib/__init__.py
cntk/contrib/crosstalk/__init__.py
cntk/contrib/crosstalk/crosstalk_cntk.py
cntk/contrib/crosstalk/crosstalk_tensorflow.py
cntk/contrib/crosstalkcaffe/__init__.py
cntk/contrib/crosstalkcaffe/convert.py
cntk/contrib/crosstalkcaffe/adapter/__init__.py
cntk/contrib/crosstalkcaffe/adapter/baseadapter.py
cntk/contrib/crosstalkcaffe/adapter/bvlccaffe/__init__.py
cntk/contrib/crosstalkcaffe/adapter/bvlccaffe/caffe_pb2.py
cntk/contrib/crosstalkcaffe/adapter/bvlccaffe/caffeadapter.py
cntk/contrib/crosstalkcaffe/adapter/bvlccaffe/caffeimpl.py
cntk/contrib/crosstalkcaffe/tests/__init__.py
cntk/contrib/crosstalkcaffe/tests/op2cntk_test.py
cntk/contrib/crosstalkcaffe/unimodel/__init__.py
cntk/contrib/crosstalkcaffe/unimodel/cntkinstance.py
cntk/contrib/crosstalkcaffe/unimodel/cntkmodel.py
cntk/contrib/crosstalkcaffe/utils/__init__.py
cntk/contrib/crosstalkcaffe/utils/format.py
cntk/contrib/crosstalkcaffe/utils/globalconf.py
cntk/contrib/crosstalkcaffe/validation/__init__.py
cntk/contrib/crosstalkcaffe/validation/validcaffe.py
cntk/contrib/crosstalkcaffe/validation/validcore.py
cntk/contrib/deeprl/__init__.py
cntk/contrib/deeprl/agent/__init__.py
cntk/contrib/deeprl/agent/agent.py
cntk/contrib/deeprl/agent/agent_factory.py
cntk/contrib/deeprl/agent/policy_gradient.py
cntk/contrib/deeprl/agent/qlearning.py
cntk/contrib/deeprl/agent/random_agent.py
cntk/contrib/deeprl/agent/tabular_qlearning.py
cntk/contrib/deeprl/agent/shared/__init__.py
cntk/contrib/deeprl/agent/shared/cntk_utils.py
cntk/contrib/deeprl/agent/shared/customized_models.py
cntk/contrib/deeprl/agent/shared/discretize.py
cntk/contrib/deeprl/agent/shared/models.py
cntk-2.7.dist-info/DESCRIPTION.rst
cntk-2.7.dist-info/METADATA
cntk-2.7.dist-info/RECORD
cntk-2.7.dist-info/WHEEL
cntk-2.7.dist-info/metadata.json
cntk-2.7.dist-info/top_level.txt
